{
  "schemaVersion": 1,
  "skill": {
    "name": "nz-post-tracking-helper",
    "version": "1.0.2"
  },
  "auditedAt": "2026-05-25T03:47:39.252Z",
  "validator": {
    "name": "localskills-validate",
    "version": "0.2.0"
  },
  "result": "pass-with-warnings",
  "checks": [
    "required-files",
    "schema",
    "permissions-scope",
    "prompt-injection",
    "malicious-code",
    "undeclared-network"
  ],
  "errors": [],
  "warnings": [
    {
      "check": "undeclared-network",
      "message": "SKILL.md: references \"www.nzpost.co.nz\" which is not in permissions.network"
    }
  ],
  "hashes": {
    "skill.json": "sha256:a0c161b5ffcae15aa96970bd32e099cd954cbf0a524098f929d034d085b3eeb2",
    "README.md": "sha256:115f0aa9bfdb08517d6cf51db1efaa40e791838624f545a2822469065c4a89b5",
    "SKILL.md": "sha256:835e222c42492a11e8e40216d93f659238bcdc6edf2c6a32c45a3bdee96d7be4",
    "LICENSE": "sha256:7fbf7065510cb2d472f3209ef2af964eb9eac4bb75ecfbce71062ea75f12f962",
    "CHANGELOG.md": "sha256:769fb9b951a1457aee521137a0ab10303d62ad58856b4bc44fef3facb85743dd"
  }
}
